LICENSE.txt
MANIFEST.in
README.rst
__init__.py
kernel.py
main.py
requirements.txt
setup.py
sqlite_debugging.py
background_zmq_ipython.egg-info/PKG-INFO
background_zmq_ipython.egg-info/SOURCES.txt
background_zmq_ipython.egg-info/dependency_links.txt
background_zmq_ipython.egg-info/requires.txt
background_zmq_ipython.egg-info/top_level.txt