Metadata-Version: 2.1
Name: background-zmq-ipython
Version: 1.20250819.151221
Summary: Background ZMQ IPython/Jupyter kernel
Home-page: https://github.com/albertz/background-zmq-ipython
Author: Albert Zeyer
Author-email: albzey@gmail.com
License: 2-clause BSD license
Classifier: Development Status :: 5 - Production/Stable
Classifier: Intended Audience :: Developers
Classifier: Intended Audience :: Education
Classifier: Intended Audience :: Science/Research
Classifier: License :: OSI Approved :: BSD License
Classifier: Operating System :: MacOS :: MacOS X
Classifier: Operating System :: Microsoft :: Windows
Classifier: Operating System :: POSIX
Classifier: Operating System :: Unix
Classifier: Programming Language :: Python
Classifier: Topic :: Software Development :: Libraries :: Python Modules
License-File: LICENSE.txt
